.gitignore
MANIFEST.in
README.rst
setup.cfg
setup.py
collective/__init__.py
collective.leadmedia.egg-info/PKG-INFO
collective.leadmedia.egg-info/SOURCES.txt
collective.leadmedia.egg-info/dependency_links.txt
collective.leadmedia.egg-info/entry_points.txt
collective.leadmedia.egg-info/namespace_packages.txt
collective.leadmedia.egg-info/not-zip-safe
collective.leadmedia.egg-info/paster_plugins.txt
collective.leadmedia.egg-info/requires.txt
collective.leadmedia.egg-info/top_level.txt
collective/leadmedia/__init__.py
collective/leadmedia/adapters.py
collective/leadmedia/configure.zcml
collective/leadmedia/events.py
collective/leadmedia/indexers.py
collective/leadmedia/interfaces.py
collective/leadmedia/setuphandlers.py
collective/leadmedia/tests.py
collective/leadmedia/utils.py
collective/leadmedia/behaviors/__init__.py
collective/leadmedia/behaviors/configure.zcml
collective/leadmedia/behaviors/slideshow.py
collective/leadmedia/behaviors/viewlets.py
collective/leadmedia/behaviors/templates/slideshow.pt
collective/leadmedia/behaviors/templates/slideshow_item.pt
collective/leadmedia/behaviors/templates/slideshow_listing.pt
collective/leadmedia/browser/__init__.py
collective/leadmedia/browser/configure.zcml
collective/leadmedia/browser/viewlets.py
collective/leadmedia/browser/views.py
collective/leadmedia/browser/templates/collection_media_view.pt
collective/leadmedia/browser/templates/folder_leadmedia_view.pt
collective/leadmedia/browser/templates/template_leadmedia_old.pt
collective/leadmedia/browser/viewlets_templates/leadmedia.pt
collective/leadmedia/profiles/default/browserlayer.xml
collective/leadmedia/profiles/default/catalog.xml
collective/leadmedia/profiles/default/collective_leadmedia-default.txt
collective/leadmedia/profiles/default/metadata.xml
collective/leadmedia/profiles/default/registry.xml
collective/leadmedia/profiles/default/types/Collection.xml
collective/leadmedia/profiles/default/types/Folder.xml
docs/HISTORY.txt
docs/INSTALL.txt
docs/LICENSE.GPL
docs/LICENSE.txt