Metadata-Version: 1.1
Name: collective.leadmedia
Version: 0.1
Summary: Adds a slideshow to any dexterity folderish type.
Home-page: https://github.com/collective/collective.leadmedia
Author: Andre Goncalves
Author-email: andre@intk.com
License: GPL
Download-URL: https://github.com/collective/collective.leadmedia/tarball/0.1
Keywords: Plone
Platform: UNKNOWN
Classifier: Framework :: Plone
Classifier: Programming Language :: Python
